[{"syntaxTree":{"root":{"name":"PΛQ","parent":null,"nodeType":"FORMULA","children":[{"name":"Λ","children":[{"name":"Q","parent":{"connective":"Λ","children":["Q","P"]},"nodeType":"VARIABLE","children":[],"variableValue":true},{"name":"P","parent":{"connective":"Λ","children":["Q","P"]},"nodeType":"VARIABLE","children":[],"variableValue":true}],"nodeType":"CONNECTIVE","variableValue":true}]}},"origin":[]},{"syntaxTree":{"root":{"name":"Q","parent":null,"nodeType":"VARIABLE","children":[],"variableValue":true}},"origin":["PΛQ"]},{"syntaxTree":{"root":{"name":"P","parent":null,"nodeType":"VARIABLE","children":[],"variableValue":true}},"origin":["PΛQ"]},{"syntaxTree":{"root":{"name":"QΛP","parent":null,"nodeType":"FORMULA","children":[{"name":"Λ","children":[{"name":"P","parent":{"connective":"Λ","children":["P","Q"]},"nodeType":"VARIABLE","children":[],"variableValue":true},{"name":"Q","parent":{"connective":"Λ","children":["P","Q"]},"nodeType":"VARIABLE","children":[],"variableValue":true}],"nodeType":"CONNECTIVE","variableValue":true}]}},"origin":["P","Q"]}]